LICENSE-APACHE
LICENSE-MIT
MANIFEST.in
README.rst
setup.py
selectz/__init__.py
selectz/selectz.py
selectz.egg-info/PKG-INFO
selectz.egg-info/SOURCES.txt
selectz.egg-info/dependency_links.txt
selectz.egg-info/top_level.txt
tests/__init__.py
tests/selectz_test.py