Metadata-Version: 1.1
Name: selectz
Version: 1.0.2
Summary: Select made easy
Home-page: https://github.com/pdxjohnny/selectz
Author: John Andersen
Author-email: johnandersenpdx@gmail.com
License: MIT/Apache-2.0
Keywords: networking
Platform: UNKNOWN
Classifier: Development Status :: 4 - Beta
Classifier: Intended Audience :: Developers
Classifier: License :: OSI Approved :: MIT License
Classifier: License :: OSI Approved :: Apache Software License
Classifier: Natural Language :: English
Classifier: Operating System :: OS Independent
Classifier: Programming Language :: Python :: 2.7
Classifier: Programming Language :: Python :: 3.5
Classifier: Programming Language :: Python :: 3.6
Classifier: Programming Language :: Python :: Implementation :: CPython
Classifier: Programming Language :: Python :: Implementation :: PyPy
